.travis.yml
MANIFEST.in
README.rst
buildout.cfg
buildout_requirements.txt
setup.py
versions.cfg
collective/__init__.py
collective.recipe.environment.egg-info/PKG-INFO
collective.recipe.environment.egg-info/SOURCES.txt
collective.recipe.environment.egg-info/dependency_links.txt
collective.recipe.environment.egg-info/entry_points.txt
collective.recipe.environment.egg-info/namespace_packages.txt
collective.recipe.environment.egg-info/not-zip-safe
collective.recipe.environment.egg-info/requires.txt
collective.recipe.environment.egg-info/top_level.txt
collective/recipe/__init__.py
collective/recipe/environment/__init__.py
collective/recipe/environment/tests/__init__.py
collective/recipe/environment/tests/test_docs.py
docs/HISTORY.rst