Metadata-Version: 1.1
Name: collective.recipe.environment
Version: 1.1.0
Summary: Buildout recipe to set and get environment variables.
Home-page: https://github.com/collective/collective.recipe.environment
Author: Rafael Oliveira
Author-email: rafaelbco@gmail.com
License: GPL
Keywords: zc.buildout buildout recipe
Platform: UNKNOWN
Classifier: Framework :: Buildout :: Recipe
Classifier: Framework :: Buildout
Classifier: Intended Audience :: Developers
Classifier: License :: OSI Approved :: GNU General Public License (GPL)
Classifier: Programming Language :: Python :: 2
Classifier: Programming Language :: Python :: 2.7
Classifier: Programming Language :: Python :: 3
Classifier: Programming Language :: Python :: 3.3
Classifier: Programming Language :: Python
Classifier: Topic :: Software Development :: Build Tools
